rhei/__init__.py
rhei/stopwatch.py
rhei-0.5.2.dist-info/AUTHORS
rhei-0.5.2.dist-info/LICENSE
rhei-0.5.2.dist-info/METADATA
rhei-0.5.2.dist-info/WHEEL
rhei-0.5.2.dist-info/entry_points.txt
rhei-0.5.2.dist-info/pbr.json
rhei-0.5.2.dist-info/top_level.txt
rhei-0.5.2.dist-info/RECORD
