Metadata-Version: 2.1
Name: rhei
Version: 0.5.2
Summary: Package that implements simple stopwatch class.
Home-page: https://github.com/dkrystki/rhei
Author: Damien Krystkiewicz
Author-email: damian.krystkiewicz@gmail.com
License: Apache 2.0
Platform: UNKNOWN
Classifier: Development Status :: 4 - Beta
Classifier: Intended Audience :: Developers
Classifier: Operating System :: POSIX :: Linux
Classifier: Programming Language :: Python :: 3 :: Only
Classifier: Programming Language :: Python :: 3.7
Classifier: Programming Language :: Python :: Implementation :: CPython
Requires-Python: >= 3.6
